sanskrit_heritage/__init__.py
sanskrit_heritage/config.py
sanskrit_heritage/py.typed
sanskrit_heritage/assets/bin/linux/interface2
sanskrit_heritage/assets/data/abstvaa.rem
sanskrit_heritage/assets/data/absya.rem
sanskrit_heritage/assets/data/auxi.rem
sanskrit_heritage/assets/data/auxiick.rem
sanskrit_heritage/assets/data/auxiinv.rem
sanskrit_heritage/assets/data/auxik.rem
sanskrit_heritage/assets/data/avyayafs.rem
sanskrit_heritage/assets/data/avyayais.rem
sanskrit_heritage/assets/data/cache.rem
sanskrit_heritage/assets/data/cachei.rem
sanskrit_heritage/assets/data/comp_freq.rem
sanskrit_heritage/assets/data/comp_freq.tsv
sanskrit_heritage/assets/data/comp_morph_freq.rem
sanskrit_heritage/assets/data/comp_morph_freq.tsv
sanskrit_heritage/assets/data/comp_trans_freq.rem
sanskrit_heritage/assets/data/comp_trans_freq.tsv
sanskrit_heritage/assets/data/guess_index.rem
sanskrit_heritage/assets/data/ifcs.rem
sanskrit_heritage/assets/data/iics.rem
sanskrit_heritage/assets/data/iifcs.rem
sanskrit_heritage/assets/data/iivs.rem
sanskrit_heritage/assets/data/indecls.rem
sanskrit_heritage/assets/data/indifcs.rem
sanskrit_heritage/assets/data/inftu.rem
sanskrit_heritage/assets/data/invs.rem
sanskrit_heritage/assets/data/kama.rem
sanskrit_heritage/assets/data/lexical_kridantas.rem
sanskrit_heritage/assets/data/lopaks.rem
sanskrit_heritage/assets/data/lopas.rem
sanskrit_heritage/assets/data/mw_exceptions.rem
sanskrit_heritage/assets/data/mw_index.rem
sanskrit_heritage/assets/data/nouns.rem
sanskrit_heritage/assets/data/pada_freq.rem
sanskrit_heritage/assets/data/pada_freq.tsv
sanskrit_heritage/assets/data/pada_morph_freq.rem
sanskrit_heritage/assets/data/pada_morph_freq.tsv
sanskrit_heritage/assets/data/pada_trans_freq.rem
sanskrit_heritage/assets/data/pada_trans_freq.tsv
sanskrit_heritage/assets/data/parts.rem
sanskrit_heritage/assets/data/partvocs.rem
sanskrit_heritage/assets/data/peris.rem
sanskrit_heritage/assets/data/piics.rem
sanskrit_heritage/assets/data/preverbs.rem
sanskrit_heritage-1.0.1.dist-info/licenses/LICENSE
sanskrit_heritage-1.0.1.dist-info/METADATA
sanskrit_heritage-1.0.1.dist-info/WHEEL
sanskrit_heritage-1.0.1.dist-info/entry_points.txt
sanskrit_heritage-1.0.1.dist-info/top_level.txt
sanskrit_heritage-1.0.1.dist-info/RECORD
