Metadata-Version: 2.4
Name: sanskrit-heritage
Version: 1.0.1
Summary: A Python wrapper for the Sanskrit Heritage Platform
Author-email: Sriram Krishnan <sriramk8@gmail.com>
License: GPLv3
Project-URL: Homepage, https://github.com/sriramkrishnan8/sanskrit-heritage
Project-URL: Bug Tracker, https://github.com/sriramkrishnan8/sanskrit-heritage/issues
Keywords: sanskrit,scl,nlp,segmentation,morphology,heritage
Classifier: Development Status :: 4 - Beta
Classifier: Intended Audience :: Developers
Classifier: Intended Audience :: Science/Research
Classifier: License :: OSI Approved :: GNU General Public License v3 (GPLv3)
Classifier: Programming Language :: Python :: 3
Classifier: Programming Language :: Python :: 3.9
Classifier: Programming Language :: Python :: 3.10
Classifier: Programming Language :: Python :: 3.11
Classifier: Operating System :: POSIX :: Linux
Classifier: Operating System :: MacOS
Classifier: Topic :: Text Processing :: Linguistic
Requires-Python: >=3.9
License-File: LICENSE
Requires-Dist: psutil>=5.0.0
Requires-Dist: devtrans>=3.0.0
Requires-Dist: requests>=2.25.0
Requires-Dist: tqdm>=4.0.0
Dynamic: license-file
